micropython_kx132/__init__.py
micropython_kx132/i2c_helpers.py
micropython_kx132/kx132.py
micropython_kx132-0.1.2.dist-info/LICENSE
micropython_kx132-0.1.2.dist-info/METADATA
micropython_kx132-0.1.2.dist-info/WHEEL
micropython_kx132-0.1.2.dist-info/top_level.txt
micropython_kx132-0.1.2.dist-info/RECORD
